MANIFEST.in
README.txt
buildout.cfg
setup.py
src/s3web/__init__.py
src/s3web/_version.py
src/s3web/base.py
src/s3web/script.py
src/s3web.egg-info/PKG-INFO
src/s3web.egg-info/SOURCES.txt
src/s3web.egg-info/dependency_links.txt
src/s3web.egg-info/entry_points.txt
src/s3web.egg-info/not-zip-safe
src/s3web.egg-info/requires.txt
src/s3web.egg-info/top_level.txt