Metadata-Version: 1.0
Name: s3web
Version: 0.1.2
Summary: Simple upload files to amazon s3 as a website
Home-page: UNKNOWN
Author: Jake Hickenlooper
Author-email: jake@weboftomorrow.com
License: UNKNOWN
Platform: UNKNOWN
